sentimind/__init__.py
sentimind/client.py
sentimind-0.1.4.dist-info/METADATA
sentimind-0.1.4.dist-info/WHEEL
sentimind-0.1.4.dist-info/top_level.txt
sentimind-0.1.4.dist-info/RECORD
