Metadata-Version: 2.4
Name: sentimind
Version: 0.1.4
Summary: Python SDK for Sentimind sentiment analysis API
Author-email: "Caerus Technical Solutions, Inc" <caerustech.solutions@gmail.com>
License: MIT
Classifier: Programming Language :: Python :: 3
Classifier: License :: OSI Approved :: MIT License
Classifier: Operating System :: OS Independent
Requires-Python: >=3.8
Requires-Dist: requests>=2.28
